MANIFEST.in
readme.rst
requirements.txt
setup.py
benzo/__init__.py
benzo/cmdline.py
benzo/config.py
benzo/editor.py
benzo/exceptions.py
benzo/formatter.py
benzo/sessions.py
benzo/template.py
benzo.egg-info/PKG-INFO
benzo.egg-info/SOURCES.txt
benzo.egg-info/dependency_links.txt
benzo.egg-info/entry_points.txt
benzo.egg-info/requires.txt
benzo.egg-info/top_level.txt
benzo/formatters/__init__.py
benzo/formatters/form.py
benzo/formatters/json.py
benzo/formatters/yaml.py
benzo/templates/__init__.py
benzo/templates/default/__init__.py
benzo/templates/default/form.py
benzo/templates/default/json.py
benzo/templates/default/yaml.py
benzo/templates/twilio/__init__.py
benzo/templates/twilio/sms.py
benzo/templates/urbanairship/__init__.py
benzo/templates/urbanairship/push.py