Metadata-Version: 1.1
Name: benzo
Version: 0.1.0
Summary: Hand-curate your artisanal REST requests more easily.
Home-page: https://github.com/coddingtonbear/benzo
Author: Adam Coddington
Author-email: me@adamcoddington.net
License: UNKNOWN
Platform: UNKNOWN
Classifier: License :: OSI Approved :: MIT License
Classifier: Operating System :: OS Independent
Classifier: Programming Language :: Python :: 3
